Dropbox_module_setup/Script.py
Dropbox_module_setup/__init__.py
Simle_Dropbox-1.0.4.dist-info/LICENSE
Simle_Dropbox-1.0.4.dist-info/METADATA
Simle_Dropbox-1.0.4.dist-info/WHEEL
Simle_Dropbox-1.0.4.dist-info/top_level.txt
Simle_Dropbox-1.0.4.dist-info/RECORD
