Metadata-Version: 2.1
Name: Simle_Dropbox
Version: 1.0.4
Summary: Un accès plus simple mais moins complet à Dropbox
Home-page: https://github.com/Grivy16/Dropbox_module.git
Author: Grivy16
Author-email: grivy16publix@gmail.com
Classifier: Programming Language :: Python :: 3
Classifier: License :: OSI Approved :: MIT License
Classifier: Operating System :: OS Independent
Requires-Python: >=3.6
License-File: LICENSE
